convert_epub/__init__.py
convert_epub/epub_extract.py
convert_epub/epub_structure.py
convert_epub/py.typed
convert_epub-0.1.0.dist-info/WHEEL
convert_epub-0.1.0.dist-info/METADATA
convert_epub-0.1.0.dist-info/RECORD
