Metadata-Version: 2.3
Name: convert-epub
Version: 0.1.0
Summary: Add your description here
Author: Maxwell Ludden
Author-email: Maxwell Ludden <max@ludden.dev>
Requires-Dist: duckdb>=1.4.3
Requires-Dist: ebooklib>=0.20
Requires-Dist: loguru>=0.7.3
Requires-Dist: pydantic>=2.12.5
Requires-Dist: pytest>=9.0.2
Requires-Dist: rich>=14.2.0
Requires-Dist: rich-gradient>=0.3.9
Requires-Dist: typer>=0.20.1
Requires-Python: >=3.14
